Metadata-Version: 2.1
Name: train-image-package
Version: 0.1
Summary: No description
Home-page: https://github.com/HoangDuy09042001/TrainModelPackage.git
Author: Duy
Author-email: hoangtanduynx@gmail.com
